{"version":"0.2.0","rank":18,"net":"271569","added":"671492","deleted":"399923","chars":{"0":2650,"1":1580,"2":1193,"3":540,"4":542,"5":520,"6":380,"7":310,"8":432,"9":282,"\n":18893,"[":706,"d":10840,"e":49033,"v":3143,"-":4443,"p":14275,"n":23324,"c":12668,"i":25514,"s":26889,"]":723,"r":24734,"u":12791,"t":40791,"f":9352,"m":9307," ":143794,"=":4278,"\"":5872,".":14952,"o":25723,":":12355,"h":6182,"/":2424,"g":7216,"b":4834,"k":2752,"y":5213,"a":25295,"l":17197,"x":4946,"w":3280,"R":1376,"_":10088,"\\":117,"$":84,",":5137,"^":16,"*":623,"(":5803,"?":521,"!":294,")":5915,"#":1366,"{":2336,"}":2423,"C":1333,"W":189,"Q":31,"S":2746,"O":3125,"L":834,"z":643,"T":2828,"M":942,";":2597,"|":108,"I":3743,"U":929,"&":688,"E":1643,"P":4064,"`":519,"A":1675,"Y":139,"N":980,"G":2431,"'":516,">":1805,"+":262,"V":2201,"<":1158,"D":984,"B":709,"X":254,"K":104,"%":299,"q":469,"j":504,"F":907,"J":181,"H":241,"@":185,"Z":62,"~":755,"ã":2,"’":1,"°":2,"\t":1072},"rankBuffer":4310,"languages":[{"language":"rust","added":74457,"deleted":59181},{"language":"typescript","added":36028,"deleted":25295},{"language":"json","added":22270,"deleted":21646},{"language":"unknown","added":112350,"deleted":67721},{"language":"javascript","added":6095,"deleted":4660},{"language":"html","added":612,"deleted":76},{"language":"plaintext","added":724,"deleted":199},{"language":"typescriptreact","added":48198,"deleted":27420},{"language":"css","added":17049,"deleted":10010},{"language":"toml","added":2875,"deleted":1054},{"language":"python","added":349458,"deleted":182556},{"language":"markdown","added":0,"deleted":1},{"language":"restructuredtext","added":1376,"deleted":104}]}